MANIFEST.in
README
setup.py
adminfilters/__init__.py
adminfilters/admin.py
django_admin_filters.egg-info/PKG-INFO
django_admin_filters.egg-info/SOURCES.txt
django_admin_filters.egg-info/dependency_links.txt
django_admin_filters.egg-info/not-zip-safe
django_admin_filters.egg-info/top_level.txt