Metadata-Version: 1.0
Name: django-admin-filters
Version: 0.1.2
Summary: Django Admin Filters
Home-page: http://github.com/ojii/django-admin-filters
Author: Jonas Obrist
Author-email: jonas.obrist@divio.ch
License: UNKNOWN
Platform: UNKNOWN
